handymodules/__init__.py
handymodules/create_logger.py
handymodules/downloading_file.py
handymodules/files_info.py
handymodules/hashing_passwords.py
handymodules/password_validation.py
handymodules/tictoc.py
handymodules-2.0.1.dist-info/LICENSE.txt
handymodules-2.0.1.dist-info/METADATA
handymodules-2.0.1.dist-info/WHEEL
handymodules-2.0.1.dist-info/top_level.txt
handymodules-2.0.1.dist-info/RECORD
