Metadata-Version: 2.1
Name: handymodules
Version: 2.0.1
Summary: A few handy, useful python modules
Home-page: https://pypi.org/project/handymodules/
Author: Adam Wasilewski
Author-email: adam@wasilewski.pw
License: UNKNOWN
Platform: UNKNOWN
Classifier: Programming Language :: Python :: 3.6
Classifier: License :: OSI Approved :: MIT License
Classifier: Operating System :: OS Independent
